nidhi_tts/__init__.py
nidhi_tts/auth.py
nidhi_tts/nidhi.py
nidhi_tts-4.2.4.dist-info/METADATA
nidhi_tts-4.2.4.dist-info/WHEEL
nidhi_tts-4.2.4.dist-info/top_level.txt
nidhi_tts-4.2.4.dist-info/RECORD
