Metadata-Version: 2.1
Name: nidhi-tts
Version: 4.2.4
Summary: A perfect Text To Speech TTS engine for tts tasks and variety of neural voices
Home-page: https://sandeshai.in/nidhi-tts
Author: Sandesh Kumar
Author-email: connect@sandeshai.in
Classifier: Programming Language :: Python :: 3
Classifier: Operating System :: OS Independent
Requires-Python: >=3.10
Requires-Dist: numpy
Requires-Dist: requests
Requires-Dist: python-dotenv
Requires-Dist: soundfile
Requires-Dist: keyboard
